uiuc_apartments/__init__.py
uiuc_apartments/shared.py
uiuc_apartments/agencies/__init__.py
uiuc_apartments/agencies/american_campus.py
uiuc_apartments/agencies/appfolio.py
uiuc_apartments/agencies/bailey.py
uiuc_apartments/agencies/bankier.py
uiuc_apartments/agencies/green_st.py
uiuc_apartments/agencies/jsj.py
uiuc_apartments/agencies/jsm.py
uiuc_apartments/agencies/mhm.py
uiuc_apartments/agencies/roland.py
uiuc_apartments/agencies/smile.py
uiuc_apartments/agencies/smith.py
uiuc_apartments/agencies/ugroup.py
uiuc_apartments/agencies/wampler.py
uiuc_apartments-0.0.7.dist-info/METADATA
uiuc_apartments-0.0.7.dist-info/WHEEL
uiuc_apartments-0.0.7.dist-info/top_level.txt
uiuc_apartments-0.0.7.dist-info/RECORD
