Metadata-Version: 2.1
Name: uiuc-apartments
Version: 0.0.7
Summary: A wrapper around a webscraper for popular rental agencies on UIUC campus
Author-email: Pete Stenger <pete@stenger.io>, Richard Liu <richy.liu.2002@gmail.com>, Hassam Uddin <hassamuddin20@gmail.com>
Project-URL: Homepage, https://github.com/reteps/uiuc_apartments
Project-URL: Bug Tracker, https://github.com/reteps/uiuc_apartments/issues
Classifier: Programming Language :: Python :: 3
Classifier: License :: OSI Approved :: MIT License
Classifier: Operating System :: OS Independent
Requires-Python: >=3.6
Requires-Dist: requests
Requires-Dist: bs4
